stribor/__init__.py
stribor/flow.py
stribor/dist/__init__.py
stribor/dist/normal.py
stribor/dist/uniform.py
stribor/flows/__init__.py
stribor/flows/activations.py
stribor/flows/affine.py
stribor/flows/cnf.py
stribor/flows/coupling.py
stribor/flows/cumsum.py
stribor/flows/identity.py
stribor/flows/iresnet.py
stribor/flows/permute.py
stribor/flows/sigmoid.py
stribor/flows/spline.py
stribor/net/__init__.py
stribor/net/attention.py
stribor/net/diagjac.py
stribor/net/diffeq.py
stribor/net/diffeq_exact_trace.py
stribor/net/diffeq_zero_trace.py
stribor/net/equivariant.py
stribor/net/made.py
stribor/net/mlp.py
stribor/net/resnet.py
stribor/net/time_net.py
stribor/test/__init__.py
stribor/test/base.py
stribor/test/test_activations.py
stribor/test/test_affine.py
stribor/test/test_attention.py
stribor/test/test_coupling.py
stribor/test/test_cumsum.py
stribor/test/test_diffeq.py
stribor/test/test_diffeq_exact_trace.py
stribor/test/test_diffeq_zero_trace.py
stribor/test/test_dist.py
stribor/test/test_divergence_computation.py
stribor/test/test_equivariant_net.py
stribor/test/test_exclusive.py
stribor/test/test_identity.py
stribor/test/test_made.py
stribor/test/test_mask.py
stribor/test/test_neural_flow.py
stribor/test/test_normalizing_flow.py
stribor/test/test_permute.py
stribor/test/test_resnet.py
stribor/test/test_sigmoid.py
stribor/test/test_spline.py
stribor/test/test_time_derivative.py
stribor/util/__init__.py
stribor/util/cubic_spline.py
stribor/util/divergence.py
stribor/util/flatten_params.py
stribor/util/mask.py
stribor/util/rational_quadratic_spline.py
stribor/util/safe_softmax.py
stribor/util/search_sorted.py
stribor-0.2.0.dist-info/LICENSE
stribor-0.2.0.dist-info/METADATA
stribor-0.2.0.dist-info/WHEEL
stribor-0.2.0.dist-info/top_level.txt
stribor-0.2.0.dist-info/RECORD
