Metadata-Version: 2.1
Name: stribor
Version: 0.2.0
Summary: Library for normalizing flows and neural flows
Home-page: https://github.com/mbilos/stribor
Author: Marin Bilos
Author-email: bilos@in.tum.de
License: UNKNOWN
Platform: UNKNOWN
Requires-Python: >=3.7
License-File: LICENSE
Requires-Dist: numpy
Requires-Dist: pytest
Requires-Dist: scipy
Requires-Dist: torch (>=1.8.0)
Requires-Dist: torchdiffeq (==0.2.2)
Requires-Dist: torchtyping (==0.1.4)
